{
    "MEGCoordinateSystem": "CTF",
    "MEGCoordinateUnits": "cm",
    "HeadCoilCoordinates": {
        "NAS": [
            6.978,
            7.32829,
            -24.7029
        ],
        "LPA": [
            -4.55085,
            6.26717,
            -27.3314
        ],
        "RPA": [
            4.99079,
            -4.11005,
            -26.4728
        ]
    },
    "HeadCoilCoordinateSystem": "CTF",
    "HeadCoilCoordinateUnits": "cm",
    "HeadCoilCoordinateSystemDescription": "Axes orientation is ALS; DEWAR",
    "IntendedFor": "/data/NIMH_ses-01_T1w.nii",
    "AnatomicalLandmarkCoordinates": {
        "NAS": [
            0.4380035,
            -134.585,
            16.672
        ],
        "LPA": [
            70.438,
            -47.58501,
            -19.328
        ],
        "RPA": [
            -73.562,
            -51.58501,
            -19.328
        ]
    },
    "AnatomicalLandmarkCoordinateSystem": "Other",
    "AnatomicalLandmarkCoordinateUnits": "mm",
    "AnatomicalLandmarkCoordinateSystemDescription": "LPS is the anatomical coordinate system"
}