{
    "MEGCoordinateSystem": "CTF",
    "MEGCoordinateUnits": "cm",
    "HeadCoilCoordinates": {
        "NAS": [
            6.75108,
            7.71799,
            -24.6056
        ],
        "LPA": [
            -4.26679,
            5.67735,
            -26.5592
        ],
        "RPA": [
            6.23953,
            -3.88827,
            -25.6092
        ]
    },
    "HeadCoilCoordinateSystem": "CTF",
    "HeadCoilCoordinateUnits": "cm",
    "HeadCoilCoordinateSystemDescription": "Axes orientation is ALS; DEWAR",
    "IntendedFor": "/data/NIMH_ses-01_T1w.nii",
    "AnatomicalLandmarkCoordinates": {
        "NAS": [
            2.771996,
            -128.8465,
            -10.8701
        ],
        "LPA": [
            63.972,
            -40.25169,
            -37.23761
        ],
        "RPA": [
            -75.228,
            -50.7987,
            -41.45641
        ]
    },
    "AnatomicalLandmarkCoordinateSystem": "Other",
    "AnatomicalLandmarkCoordinateUnits": "mm",
    "AnatomicalLandmarkCoordinateSystemDescription": "LPS is the anatomical coordinate system"
}